
<NikuDataBus xmlns:xsi="http://www.w3.org/2001/XMLSchema-instance" xsi:noNamespaceSchemaLocation="../xsd/nikuxog_contentPack.xsd"><Header action="write" externalSource="NIKU" objectType="contentPack" version="13.3.0.286"/><contentPack update="true"><Processes><Process allowOneRunningInstance="false" code="cabr_financial_bloqueia" createdBy="admprj" endStep="Término" source="customer"
    startOption="ON_DEMAND" startStep="Início"><nls description="Bloqueia campos do objeto principal da integração financeira" languageCode="cs" name="CABR Financial - Bloqueia Campos"/><nls description="Bloqueia campos do objeto principal da integração financeira" languageCode="da" name="CABR Financial - Bloqueia Campos"/><nls description="Bloqueia campos do objeto principal da integração financeira" languageCode="de" name="CABR Financial - Bloqueia Campos"/><nls description="Bloqueia campos do objeto principal da integração financeira" languageCode="en" name="CABR Financial - Bloqueia Campos"/><nls description="Bloqueia campos do objeto principal da integração financeira" languageCode="es" name="CABR Financial - Bloqueia Campos"/><nls description="Bloqueia campos do objeto principal da integração financeira" languageCode="fi" name="CABR Financial - Bloqueia Campos"/><nls description="Bloqueia campos do objeto principal da integração financeira" languageCode="fr" name="CABR Financial - Bloqueia Campos"/><nls description="Bloqueia campos do objeto principal da integração financeira" languageCode="hu" name="CABR Financial - Bloqueia Campos"/><nls description="Bloqueia campos do objeto principal da integração financeira" languageCode="it" name="CABR Financial - Bloqueia Campos"/><nls description="Bloqueia campos do objeto principal da integração financeira" languageCode="ja" name="CABR Financial - Bloqueia Campos"/><nls description="Bloqueia campos do objeto principal da integração financeira" languageCode="ko" name="CABR Financial - Bloqueia Campos"/><nls description="Bloqueia campos do objeto principal da integração financeira" languageCode="nl" name="CABR Financial - Bloqueia Campos"/><nls description="Bloqueia campos do objeto principal da integração financeira" languageCode="no" name="CABR Financial - Bloqueia Campos"/><nls description="Bloqueia campos do objeto principal da integração financeira" languageCode="pl" name="CABR Financial - Bloqueia Campos"/><nls description="Bloqueia campos do objeto principal da integração financeira" languageCode="pt" name="CABR Financial - Bloqueia Campos"/><nls description="Bloqueia campos do objeto principal da integração financeira" languageCode="ru" name="CABR Financial - Bloqueia Campos"/><nls description="Bloqueia campos do objeto principal da integração financeira" languageCode="sv" name="CABR Financial - Bloqueia Campos"/><nls description="Bloqueia campos do objeto principal da integração financeira" languageCode="tr" name="CABR Financial - Bloqueia Campos"/><nls description="Bloqueia campos do objeto principal da integração financeira" languageCode="zh" name="CABR Financial - Bloqueia Campos"/><nls description="Bloqueia campos do objeto principal da integração financeira" languageCode="zh_TW" name="CABR Financial - Bloqueia Campos"/><Security><GroupSecurity groupCode="rnv_administrador" rightCode="PROCESS-DEF-INST-START"/><GroupSecurity groupCode="rnv_administrador" rightCode="PROCESS-RUN-INST-CANCEL"/><GroupSecurity groupCode="rnv_administrador" rightCode="PROCESS-RUN-INST-DELETE"/><UserSecurity rightCode="PROCESS-DEF-INST-INITIATE" userName="admprj"/><UserSecurity rightCode="PROCESS-DEF-INST-WRITE" userName="admprj"/></Security><Objects><Object manualStart="true" name="this" objectType="cabr_int_financials" partitionCode="NIKU.ROOT" partitionModeCode="PARTITION_ONLY" type="BPM_POT_PRIMARY"/></Objects><Steps><Step id="Início" isMileStone="false" sequenceNo="1"><nls languageCode="cs" name="Início"/><nls languageCode="da" name="Início"/><nls languageCode="de" name="Início"/><nls languageCode="en" name="Início"/><nls languageCode="es" name="Início"/><nls languageCode="fi" name="Início"/><nls languageCode="fr" name="Início"/><nls languageCode="hu" name="Início"/><nls languageCode="it" name="Início"/><nls languageCode="ja" name="Início"/><nls languageCode="ko" name="Início"/><nls languageCode="nl" name="Início"/><nls languageCode="no" name="Início"/><nls languageCode="pl" name="Início"/><nls languageCode="pt" name="Início"/><nls languageCode="ru" name="Início"/><nls languageCode="sv" name="Início"/><nls languageCode="tr" name="Início"/><nls languageCode="zh" name="Início"/><nls languageCode="zh_TW" name="Início"/><Notifications notifyOwner="false"><NotifyWhen stepCompleted="false" stepInError="false" stepStarted="false"/><Assignees/></Notifications><Operations><Action code="bloqueia" objectMethod="lock" objectName="this" type="BPM_SAT_SYSTEM"><nls languageCode="cs" name="bloqueia"/><nls languageCode="da" name="bloqueia"/><nls languageCode="de" name="bloqueia"/><nls languageCode="en" name="bloqueia"/><nls languageCode="es" name="bloqueia"/><nls languageCode="fi" name="bloqueia"/><nls languageCode="fr" name="bloqueia"/><nls languageCode="hu" name="bloqueia"/><nls languageCode="it" name="bloqueia"/><nls languageCode="ja" name="bloqueia"/><nls languageCode="ko" name="bloqueia"/><nls languageCode="nl" name="bloqueia"/><nls languageCode="no" name="bloqueia"/><nls languageCode="pl" name="bloqueia"/><nls languageCode="pt" name="bloqueia"/><nls languageCode="ru" name="bloqueia"/><nls languageCode="sv" name="bloqueia"/><nls languageCode="tr" name="bloqueia"/><nls languageCode="zh" name="bloqueia"/><nls languageCode="zh_TW" name="bloqueia"/><ActionParams><Param name="lock" value="cabr_import_file"/><Param name="lock" value="ckproject"/><Param name="lock" value="ckprjfinstatus"/><Param name="lock" value="ckprjstatus"/><Param name="lock" value="ckresource"/><Param name="lock" value="ckresfinstatus"/><Param name="lock" value="ckrole"/><Param name="lock" value="cktask"/><Param name="lock" value="cktskstatus"/><Param name="lock" value="cktransclass"/><Param name="lock" value="ckvendor"/><Param name="lock" value="proc_cond"/><Param name="lock" value="def_chargeable"/><Param name="lock" value="def_charge_code"/><Param name="lock" value="def_currency"/><Param name="lock" value="def_input_type_code"/><Param name="lock" value="def_transaction_type"/><Param name="lock" value="rnv_mail_error"/><Param name="lock" value="rnv_mail_wip"/><Param name="lock" value="fillrole"/><Param name="lock" value="filltclass"/><Param name="lock" value="name"/><Param name="lock" value="cashtransaction"/></ActionParams><Notifications notifyOwner="false"><NotifyWhen stepActionInError="false" stepActionPerformed="false"/><Assignees/></Notifications></Action></Operations><TransitionRestrictions><TransitionRestriction><Join type="BPM_JT_NONE"><Condition sequencNo="1" type="BPM_SCT_PRECONDITION"/></Join></TransitionRestriction><TransitionRestriction><Split type="BPM_ST_SEQUENCE"><Condition sequencNo="1" type="BPM_SCT_POSTCONDITION"><Transitions><Transition to="Término"/></Transitions></Condition></Split></TransitionRestriction></TransitionRestrictions></Step><Step id="Término" isMileStone="false" sequenceNo="2"><nls languageCode="cs" name="Término"/><nls languageCode="da" name="Término"/><nls languageCode="de" name="Término"/><nls languageCode="en" name="Término"/><nls languageCode="es" name="Término"/><nls languageCode="fi" name="Término"/><nls languageCode="fr" name="Término"/><nls languageCode="hu" name="Término"/><nls languageCode="it" name="Término"/><nls languageCode="ja" name="Término"/><nls languageCode="ko" name="Término"/><nls languageCode="nl" name="Término"/><nls languageCode="no" name="Término"/><nls languageCode="pl" name="Término"/><nls languageCode="pt" name="Término"/><nls languageCode="ru" name="Término"/><nls languageCode="sv" name="Término"/><nls languageCode="tr" name="Término"/><nls languageCode="zh" name="Término"/><nls languageCode="zh_TW" name="Término"/><Notifications notifyOwner="false"><NotifyWhen stepCompleted="false" stepInError="false" stepStarted="false"/><Assignees/></Notifications><Operations/><TransitionRestrictions><TransitionRestriction><Join type="BPM_JT_NONE"><Condition sequencNo="1" type="BPM_SCT_PRECONDITION"/></Join></TransitionRestriction><TransitionRestriction><Split type="BPM_ST_SEQUENCE"><Condition sequencNo="1" type="BPM_SCT_POSTCONDITION"><Transitions/></Condition></Split></TransitionRestriction></TransitionRestrictions></Step></Steps><Groups/><OBSAssocs complete="false"/></Process></Processes><lookups update="true"><staticLookup autoSuggestEnabled="true" autoSuggestMaxSuggestions="10" code="CAL_EVENT_PRIORITY" hiddenAttributeName="id" sortStyle="manual"
    source="niku.com" status="active" update="true"><nls description="Priorita události kalendáře" languageCode="cs" name="Priorita kalendáře"/><nls description="Prioritet for kalenderaftale" languageCode="da" name="Kalenderprioritet"/><nls description="Kalenderereignis - Priorität" languageCode="de" name="Kalenderpriorität"/><nls description="Calendar Event Priority" languageCode="en" name="Calendar Priority"/><nls description="Prioridad de los eventos del calendario" languageCode="es" name="Prioridad del calendario"/><nls description="Kalenteritapahtuman prioriteetti" languageCode="fi" name="Kalenteriprioriteetti"/><nls description="Priorité des événements du calendrier" languageCode="fr" name="Priorité sur le calendrier"/><nls description="Naptáresemény prioritása" languageCode="hu" name="Naptár prioritása"/><nls description="Priorità eventi calendario" languageCode="it" name="Priorità calendario"/><nls description="カレンダ イベントの優先度" languageCode="ja" name="カレンダの優先度"/><nls description="일정 이벤트 우선 순위" languageCode="ko" name="일정 우선 순위"/><nls description="Prioriteit agenda-evenement" languageCode="nl" name="Agenda prioriteit"/><nls description="Kalenderbegivenhetsprioritet" languageCode="no" name="Kalenderprioritet"/><nls description="Priorytet zdarzenia w kalendarzu" languageCode="pl" name="Priorytet kalendarza"/><nls description="Prioridade do evento do calendário" languageCode="pt" name="Prioridade do calendário"/><nls description="Приоритет события календаря" languageCode="ru" name="Приоритет календаря"/><nls description="Prioritet för kalenderhändelse" languageCode="sv" name="Kalenderprioritet"/><nls description="Takvim Olayı Önceliği" languageCode="tr" name="Takvim Önceliği"/><nls description="日历事件优先级" languageCode="zh" name="日历优先级"/><nls description="行事曆事件優先順序" languageCode="zh_TW" name="行事曆優先順序"/><lookupValue code="CAL_LOW" sortOrder="1" status="active"><nls description="Nízké" languageCode="cs" name="Nízké"/><nls description="Lav" languageCode="da" name="Lav"/><nls description="Niedrig" languageCode="de" name="Niedrig"/><nls description="Low" languageCode="en" name="Low"/><nls description="Bajo" languageCode="es" name="Bajo"/><nls description="Matala" languageCode="fi" name="Matala"/><nls description="Faible" languageCode="fr" name="Faible"/><nls description="Alacsony" languageCode="hu" name="Alacsony"/><nls description="Bassa" languageCode="it" name="Bassa"/><nls description="低" languageCode="ja" name="低"/><nls description="낮음" languageCode="ko" name="낮음"/><nls description="Laag" languageCode="nl" name="Laag"/><nls description="Lav" languageCode="no" name="Lav"/><nls description="Niski" languageCode="pl" name="Niski"/><nls description="Baixo" languageCode="pt" name="Baixo"/><nls description="Низкий" languageCode="ru" name="Низкий"/><nls description="Låg" languageCode="sv" name="Låg"/><nls description="Düşük" languageCode="tr" name="Düşük"/><nls description="低" languageCode="zh" name="低"/><nls description="低" languageCode="zh_TW" name="低"/></lookupValue><lookupValue code="CAL_MEDIUM" sortOrder="2" status="active"><nls description="Střední" languageCode="cs" name="Střední"/><nls description="Mellem" languageCode="da" name="Mellem"/><nls description="Mittel" languageCode="de" name="Mittel"/><nls description="Medium" languageCode="en" name="Medium"/><nls description="Medio" languageCode="es" name="Medio"/><nls description="Keskisuuri" languageCode="fi" name="Keskisuuri"/><nls description="Moyen(ne)" languageCode="fr" name="Moyen(ne)"/><nls description="Közepes" languageCode="hu" name="Közepes"/><nls description="Media" languageCode="it" name="Media"/><nls description="中" languageCode="ja" name="中"/><nls description="중간" languageCode="ko" name="중간"/><nls description="Gemiddeld" languageCode="nl" name="Gemiddeld"/><nls description="Middels" languageCode="no" name="Middels"/><nls description="Średni" languageCode="pl" name="Średni"/><nls description="Médio" languageCode="pt" name="Médio"/><nls description="Средний" languageCode="ru" name="Средний"/><nls description="Medel" languageCode="sv" name="Medel"/><nls description="Orta" languageCode="tr" name="Orta"/><nls description="中" languageCode="zh" name="中"/><nls description="中" languageCode="zh_TW" name="中"/></lookupValue><lookupValue code="CAL_HIGH" sortOrder="3" status="active"><nls description="Vysoké" languageCode="cs" name="Vysoké"/><nls description="Høj" languageCode="da" name="Høj"/><nls description="Hoch" languageCode="de" name="Hoch"/><nls description="High" languageCode="en" name="High"/><nls description="Alto" languageCode="es" name="Alto"/><nls description="Korkea" languageCode="fi" name="Korkea"/><nls description="Elevé(e)" languageCode="fr" name="Elevé(e)"/><nls description="Magas" languageCode="hu" name="Magas"/><nls description="Alta" languageCode="it" name="Alta"/><nls description="高" languageCode="ja" name="高"/><nls description="높음" languageCode="ko" name="높음"/><nls description="Hoog" languageCode="nl" name="Hoog"/><nls description="Høy" languageCode="no" name="Høy"/><nls description="Wysoki" languageCode="pl" name="Wysoki"/><nls description="Alto" languageCode="pt" name="Alto"/><nls description="Высокий" languageCode="ru" name="Высокий"/><nls description="Hög" languageCode="sv" name="Hög"/><nls description="Yüksek" languageCode="tr" name="Yüksek"/><nls description="高" languageCode="zh" name="高"/><nls description="高" languageCode="zh_TW" name="高"/></lookupValue><displayedSuggestionAttributes><displayedSuggestionAttribute value="name"/></displayedSuggestionAttributes><searchedSuggestionAttributes><searchedSuggestionAttribute value="name"/></searchedSuggestionAttributes></staticLookup></lookups></contentPack><XOGOutput> <Object type="contentPack"/> <Status state="SUCCESS"/> <Statistics insertedRecords="0" failureRecords="0" totalNumberOfRecords="2" updatedRecords="0"/> <Records/> </XOGOutput></NikuDataBus>